sensitive_data_detector/__init__.py
sensitive_data_detector/config.json
sensitive_data_detector/content_analyze.py
sensitive_data_detector/file_reader.py
sensitive_data_detector/load_patterns.py
sensitive_data_detector/sensitive_check.py
sensitive_data_detector/version.py
sensitive_data_detector-1.1.0.dist-info/licenses/LICENSE
sensitive_data_detector-1.1.0.dist-info/METADATA
sensitive_data_detector-1.1.0.dist-info/WHEEL
sensitive_data_detector-1.1.0.dist-info/top_level.txt
sensitive_data_detector-1.1.0.dist-info/RECORD
